odoo10_addon_shopinvader_product_media-10.0.1.0.0.99.dev5-py3.8-nspkg.pth
odoo/addons/shopinvader_product_media/README.rst
odoo/addons/shopinvader_product_media/__init__.py
odoo/addons/shopinvader_product_media/__manifest__.py
odoo/addons/shopinvader_product_media/data/ir_product_export.xml
odoo/addons/shopinvader_product_media/i18n/shopinvader_product_media.pot
odoo10_addon_shopinvader_product_media-10.0.1.0.0.99.dev5.dist-info/METADATA
odoo10_addon_shopinvader_product_media-10.0.1.0.0.99.dev5.dist-info/WHEEL
odoo10_addon_shopinvader_product_media-10.0.1.0.0.99.dev5.dist-info/namespace_packages.txt
odoo10_addon_shopinvader_product_media-10.0.1.0.0.99.dev5.dist-info/top_level.txt
odoo10_addon_shopinvader_product_media-10.0.1.0.0.99.dev5.dist-info/RECORD
