Metadata-Version: 2.1
Name: odoo10-addon-shopinvader-product-media
Version: 10.0.1.0.0.99.dev5
Summary: Shopinvader Product Media
Home-page: https://github.com/shopinvader/odoo-shopinvader
Author: Akretion
License: AGPL-3
Platform: UNKNOWN
Classifier: Programming Language :: Python
Classifier: Framework :: Odoo
Classifier: License :: OSI Approved :: GNU Affero General Public License v3
Requires-Python: ~=2.7
Requires-Dist: odoo10-addon-shopinvader
Requires-Dist: odoo10-addon-storage-media-product
Requires-Dist: odoo (<10.1dev,>=10.0)
